image_processing_jaderjf/__init__.py
image_processing_jaderjf/processing/__init__.py
image_processing_jaderjf/processing/combination.py
image_processing_jaderjf/processing/transformation.py
image_processing_jaderjf/utils/__init__.py
image_processing_jaderjf/utils/io.py
image_processing_jaderjf/utils/plot.py
image_processing_jaderjf-0.0.1.dist-info/METADATA
image_processing_jaderjf-0.0.1.dist-info/WHEEL
image_processing_jaderjf-0.0.1.dist-info/top_level.txt
image_processing_jaderjf-0.0.1.dist-info/RECORD
