Metadata-Version: 2.1
Name: image_processing_jaderjf
Version: 0.0.1
Summary: image processing package using skimage
Home-page: https://github.com/JaderJFranca/image-processing
Author: JaderJFranca
Requires-Python: >=3.0
Requires-Dist: matplotlib
Requires-Dist: numpy
Requires-Dist: scikit-image
